<?xml version="1.0" encoding="UTF-8"?>
<JdbcEntitySetup
	xmlns="http://www.ontimize.com/schema/jdbc"
	xmlns:xsi="http://www.w3.org/2001/XMLSchema-instance"
	xsi:schemaLocation="http://www.ontimize.com/schema/jdbc http://www.ontimize.com/schema/jdbc/ontimize-jdbc-dao.xsd"
	catalog="" schema="${mainschema}" table="tuser_role"
	datasource="mainDataSource" sqlhandler="dbSQLStatementHandler">
	<DeleteKeys>
		<Column>id</Column>
	</DeleteKeys>
	<UpdateKeys>
		<Column>id</Column>
	</UpdateKeys>
	<Queries>
		<Query id="login">
			<Sentence>
                <![CDATA[
                    SELECT
                        #COLUMNS#
                    FROM ${mainschema}.tuser
                    #WHERE#
                    #ORDER#
                ]]>
            </Sentence>
		</Query>
		<Query id="userRole">
			<AmbiguousColumns>
				<AmbiguousColumn name="user_" prefix="tu" />
				<AmbiguousColumn name="id" prefix="tr" />
				<AmbiguousColumn name="id" prefix="tur" />
			</AmbiguousColumns>
			<Sentence>
					<![CDATA[
					select
						#COLUMNS#
					from
						${mainschema}.tuser tu
						JOIN ${mainschema}.tuser_role tur ON tu.user_ = tur.user_name
						JOIN ${mainschema}.trole tr ON tur.id_role = tr.id
					#WHERE#
					#ORDER#
					]]>
			</Sentence>
		</Query>
		<Query id="serverPermissions">
			<AmbiguousColumns>
				<AmbiguousColumn name="id" prefix="tr" />
				<AmbiguousColumn name="id" prefix="tsp" />
				<AmbiguousColumn name="id" prefix="trsp" />
			</AmbiguousColumns>
			<Sentence>
					<![CDATA[
					select
						#COLUMNS#
					from
						${mainschema}.trole trl
						JOIN ${mainschema}.trole_server_permission trsp ON trl.id = trsp.id_rolename
						JOIN ${mainschema}.tserver_permission tsp ON trsp.id_server_permission = tsp.id
					#WHERE#
					#ORDER#
					]]>
		</Sentence>
		</Query>
		<Query id="clientPermissions">
			<Sentence>
					<![CDATA[
					select
						#COLUMNS#
					from
						${mainschema}.trole tr
					#WHERE#
					#ORDER#
					]]>
		</Sentence>
		</Query>
	</Queries>
</JdbcEntitySetup>